pylama_pylint/__init__.py
pylama_pylint/main.py
pylama_pylint/pylint.rc
pylama_pylint-3.1.1.dist-info/LICENSE
pylama_pylint-3.1.1.dist-info/METADATA
pylama_pylint-3.1.1.dist-info/WHEEL
pylama_pylint-3.1.1.dist-info/entry_points.txt
pylama_pylint-3.1.1.dist-info/top_level.txt
pylama_pylint-3.1.1.dist-info/RECORD
