Metadata-Version: 2.1
Name: pylama-pylint
Version: 3.1.1
Summary: Pylint integration to pylama library.
Home-page: http://github.com/klen/pylama_pylint
Author: Kirill Klenov
Author-email: horneds@gmail.com
License: BSD
Platform: Any
Classifier: Intended Audience :: Developers
Classifier: License :: OSI Approved :: BSD License
Classifier: Operating System :: OS Independent
Classifier: Programming Language :: Python
Requires-Dist: pylama (>=6.3.3)
Requires-Dist: pylint (>=1.6.4)
